odoo/addons/stock_product_template_tags/README.rst
odoo/addons/stock_product_template_tags/__init__.py
odoo/addons/stock_product_template_tags/__manifest__.py
odoo/addons/stock_product_template_tags/i18n/stock_product_template_tags.pot
odoo/addons/stock_product_template_tags/readme/CONTRIBUTORS.rst
odoo/addons/stock_product_template_tags/readme/DESCRIPTION.rst
odoo/addons/stock_product_template_tags/static/description/icon.png
odoo/addons/stock_product_template_tags/static/description/index.html
odoo/addons/stock_product_template_tags/views/product_template_tag.xml
odoo14_addon_stock_product_template_tags-14.0.1.1.0.dist-info/METADATA
odoo14_addon_stock_product_template_tags-14.0.1.1.0.dist-info/WHEEL
odoo14_addon_stock_product_template_tags-14.0.1.1.0.dist-info/top_level.txt
odoo14_addon_stock_product_template_tags-14.0.1.1.0.dist-info/RECORD
